intergrid/__init__.py
intergrid/intergrid.py
intergrid/test/19feb-test-intergrid.log
intergrid/test/test-intergrid.py
intergrid/test/testfuncs.py
intergrid/test/util.py
intergrid-2020.2.20.dist-info/LICENSE.BSD
intergrid-2020.2.20.dist-info/METADATA
intergrid-2020.2.20.dist-info/WHEEL
intergrid-2020.2.20.dist-info/top_level.txt
intergrid-2020.2.20.dist-info/RECORD
