Metadata-Version: 2.1
Name: intergrid
Version: 2020.2.20
Summary: Interpolate data given on an Nd box grid, uniform or non-uniform, using numpy and scipy
Home-page: https://github.com/denis-bz/intergrid.git
Author: Denis
Author-email: denis-bz-py@t-online.de
License: BSD 3-Clause License
Keywords: interpolation box-grid  rectangular-grid  python  numpy  scipy
Platform: UNKNOWN
Requires-Dist: numpy
Requires-Dist: scipy
